nmf/__init__.py
nmf/cdnmf_fast.cpython-38-darwin.so
nmf/cdnmf_fast.pyx
nmf/nmf.py
nmf/utils.py
nmf_gucky92-0.0.1.dist-info/COPYING
nmf_gucky92-0.0.1.dist-info/METADATA
nmf_gucky92-0.0.1.dist-info/WHEEL
nmf_gucky92-0.0.1.dist-info/entry_points.txt
nmf_gucky92-0.0.1.dist-info/top_level.txt
nmf_gucky92-0.0.1.dist-info/RECORD
