Metadata-Version: 2.1
Name: nmf-gucky92
Version: 0.0.1
Summary: NMF with missing values
Home-page: https://github.com/gucky92/nmf-contrib
Author: Matthias Christenson
Author-email: gucky@gucky.eu
License: BSD
Platform: UNKNOWN
Requires-Dist: cython
Requires-Dist: scikit-learn
